helm_tag_updater.py
helm_tag_updater-0.1.1.dist-info/LICENSE
helm_tag_updater-0.1.1.dist-info/METADATA
helm_tag_updater-0.1.1.dist-info/WHEEL
helm_tag_updater-0.1.1.dist-info/entry_points.txt
helm_tag_updater-0.1.1.dist-info/RECORD
