Metadata-Version: 2.1
Name: helm-tag-updater
Version: 0.1.1
Summary: A python `values.yaml` helm updater cli.
Author: Ignat Belousov
Author-email: ignat.belousov2000@yahoo.com
Requires-Python: >=3.9,<4.0
Classifier: Programming Language :: Python :: 3
Classifier: Programming Language :: Python :: 3.9
Classifier: Programming Language :: Python :: 3.10
Classifier: Programming Language :: Python :: 3.11
Requires-Dist: ruamel-yaml (>=0.17.32,<0.18.0)
